rfdocserver/__init__.py
rfdocserver/__main__.py
rfdocserver/_version.py
rfdocserver/document_generator.py
rfdocserver/server.py
rfdocserver/static/GitHub-Mark-120px-plus.png
rfdocserver/static/GitHub-Mark-32px.png
rfdocserver/static/GitHub-Mark-64px.png
rfdocserver/static/__init__.py
rfdocserver/static/logo-32px.png
rfdocserver/static/logo.png
rfdocserver/static/main.css
rfdocserver/static/reload_32px.png
rfdocserver/static/search_icon.png
rfdocserver/templates/__init__.py
rfdocserver/templates/base.html
rfdocserver/templates/index.html
rfdocserver/templates/page.html
rfdocserver/templates/search.html
rfdocserver-1.0.2.dist-info/LICENSE
rfdocserver-1.0.2.dist-info/METADATA
rfdocserver-1.0.2.dist-info/WHEEL
rfdocserver-1.0.2.dist-info/top_level.txt
rfdocserver-1.0.2.dist-info/RECORD
